typesystem/__init__.py
typesystem/base.py
typesystem/composites.py
typesystem/fields.py
typesystem/formats.py
typesystem/forms.py
typesystem/json_schema.py
typesystem/py.typed
typesystem/schemas.py
typesystem/unique.py
typesystem/templates/forms/checkbox.html
typesystem/templates/forms/input.html
typesystem/templates/forms/select.html
typesystem/templates/forms/textarea.html
typesystem/tokenize/__init__.py
typesystem/tokenize/positional_validation.py
typesystem/tokenize/tokenize_json.py
typesystem/tokenize/tokenize_yaml.py
typesystem/tokenize/tokens.py
typesystem-0.4.1.dist-info/LICENSE.md
typesystem-0.4.1.dist-info/METADATA
typesystem-0.4.1.dist-info/WHEEL
typesystem-0.4.1.dist-info/top_level.txt
typesystem-0.4.1.dist-info/RECORD
